{
  "posts": [
    {
      "id": 7,
      "labble": "vegitable-8",
      "price": 1,
      "quantity": 1
    },
    {
      "id": 9,
      "labble": "vegitable-2",
      "price": 1,
      "quantity": 1
    },
    {
      "id": 2,
      "labble": "vegitable-3",
      "price": 1,
      "quantity": 1
    },
    {
      "id": 3,
      "labble": "vegitable-4",
      "price": 1,
      "quantity": 1
    },
    {
      "id": 5,
      "labble": "vegitable-5",
      "price": 1,
      "quantity": 1
    },
    {
      "id": 6,
      "labble": "vegitable-6",
      "price": 1,
      "quantity": 1
    }
  ]
}